setup.py
rktestdist/Binomialdistribution.py
rktestdist/Gaussiandistribution.py
rktestdist/Generaldistribution.py
rktestdist/__init__.py
rktestdist.egg-info/PKG-INFO
rktestdist.egg-info/SOURCES.txt
rktestdist.egg-info/dependency_links.txt
rktestdist.egg-info/not-zip-safe
rktestdist.egg-info/top_level.txt